common_utils/__init__.py
common_utils/adv_file_utils/__init__.py
common_utils/adv_file_utils/adv_file_utils.py
common_utils/base/__init__.py
common_utils/base/basic.py
common_utils/base/prediction.py
common_utils/bash_utils/__init__.py
common_utils/bash_utils/bash_utils.py
common_utils/check_utils/__init__.py
common_utils/check_utils/check_utils.py
common_utils/common_types/__init__.py
common_utils/common_types/angle.py
common_utils/common_types/bbox.py
common_utils/common_types/bgr.py
common_utils/common_types/common.py
common_utils/common_types/keypoint.py
common_utils/common_types/point.py
common_utils/common_types/segmentation.py
common_utils/common_types/tracker/__init__.py
common_utils/common_types/tracker/tracker.py
common_utils/constants/__init__.py
common_utils/constants/color_constants.py
common_utils/constants/extension_constants.py
common_utils/constants/number_constants.py
common_utils/counter_utils/__init__.py
common_utils/counter_utils/counter_utils.py
common_utils/cv_drawing_utils/__init__.py
common_utils/cv_drawing_utils/cv_drawing_utils.py
common_utils/cv_drawing_utils/spirograph.py
common_utils/cv_viewer/__init__.py
common_utils/download_utils/__init__.py
common_utils/download_utils/download_utils.py
common_utils/error_utils/__init__.py
common_utils/error_utils/decorators/__init__.py
common_utils/error_utils/decorators/bypass.py
common_utils/file_utils/__init__.py
common_utils/file_utils/file_utils.py
common_utils/image_utils/__init__.py
common_utils/image_utils/image_utils.py
common_utils/iter_utils/__init__.py
common_utils/iter_utils/image_iter.py
common_utils/math_utils/__init__.py
common_utils/math_utils/math_utils.py
common_utils/ml_utils/__init__.py
common_utils/ml_utils/heatmap/__init__.py
common_utils/ml_utils/heatmap/heatmap.py
common_utils/ml_utils/resume/__init__.py
common_utils/ml_utils/resume/resume.py
common_utils/param_parsing_utils/__init__.py
common_utils/param_parsing_utils/parsing.py
pyclay_common_utils-0.2.6.dist-info/LICENSE
pyclay_common_utils-0.2.6.dist-info/METADATA
pyclay_common_utils-0.2.6.dist-info/WHEEL
pyclay_common_utils-0.2.6.dist-info/top_level.txt
pyclay_common_utils-0.2.6.dist-info/RECORD
