Metadata-Version: 2.1
Name: pyclay-common-utils
Version: 0.2.6
Summary: Common utilities for convenience.
Home-page: https://github.com/cm107/common_utils
Author: Clayton Mork
Author-email: mork.clayton3@gmail.com
License: MIT License
Platform: UNKNOWN
Classifier: Programming Language :: Python :: 3
Classifier: License :: OSI Approved :: MIT License
Classifier: Operating System :: OS Independent
Requires-Python: >=3.7
Requires-Dist: Cython (>=0.29.14)
Requires-Dist: opencv-python (>=4.1.1.26)
Requires-Dist: numpy (>=1.17.2)
Requires-Dist: requests (>=2.22.0)
Requires-Dist: pylint (>=2.4.2)
Requires-Dist: tqdm (>=4.36.1)
Requires-Dist: scipy (>=1.4.1)
Requires-Dist: imgaug (>=0.3.0)
Requires-Dist: PyYAML (>=5.3.1)
Requires-Dist: pyclay-logger (==0.2)
